extract_transform/__init__.py
extract_transform/aggregation/mean.py
extract_transform/aggregation/sum.py
extract_transform/aggregation/tests/test_mean.py
extract_transform/aggregation/tests/test_sum.py
extract_transform/basic_types/boolean.py
extract_transform/basic_types/decimal.py
extract_transform/basic_types/float.py
extract_transform/basic_types/hexadecimal.py
extract_transform/basic_types/integer.py
extract_transform/basic_types/raw.py
extract_transform/basic_types/string.py
extract_transform/basic_types/tests/test_boolean.py
extract_transform/basic_types/tests/test_decimal.py
extract_transform/basic_types/tests/test_float.py
extract_transform/basic_types/tests/test_hexadecimal.py
extract_transform/basic_types/tests/test_integer.py
extract_transform/basic_types/tests/test_raw.py
extract_transform/basic_types/tests/test_string.py
extract_transform/complex_types/array.py
extract_transform/complex_types/numeric_with_codes.py
extract_transform/complex_types/record.py
extract_transform/complex_types/tests/test_array.py
extract_transform/complex_types/tests/test_numeric_with_codes.py
extract_transform/complex_types/tests/test_record.py
extract_transform/data_manipulation/__init__.py
extract_transform/data_manipulation/compose.py
extract_transform/data_manipulation/count.py
extract_transform/data_manipulation/default_value.py
extract_transform/data_manipulation/dictmap.py
extract_transform/data_manipulation/exists.py
extract_transform/data_manipulation/filter.py
extract_transform/data_manipulation/flatten.py
extract_transform/data_manipulation/map_value.py
extract_transform/data_manipulation/pivot.py
extract_transform/data_manipulation/select.py
extract_transform/data_manipulation/select_list_item.py
extract_transform/data_manipulation/sort_dict_list.py
extract_transform/data_manipulation/split.py
extract_transform/data_manipulation/tests/test_compose.py
extract_transform/data_manipulation/tests/test_count.py
extract_transform-1.0.10.dist-info/LICENSE
extract_transform-1.0.10.dist-info/METADATA
extract_transform-1.0.10.dist-info/WHEEL
extract_transform-1.0.10.dist-info/RECORD
