Metadata-Version: 2.1
Name: extract-transform
Version: 1.0.10
Summary: A Python library for efficient encoding, decoding, and transformation of complex data, ideal for machine learning workflows.
Home-page: https://github.com/frederikvanhevel/extract-transform
License: MIT
Keywords: ETL,data,transformation,extraction,processing,machine,learning,pipeline
Author: Frederik Vanhevel
Author-email: frederik.vanhevel@gmail.com
Requires-Python: >=3.7,<4.0
Classifier: License :: OSI Approved :: MIT License
Classifier: Programming Language :: Python :: 3
Classifier: Programming Language :: Python :: 3.7
Classifier: Programming Language :: Python :: 3.8
Classifier: Programming Language :: Python :: 3.9
Classifier: Programming Language :: Python :: 3.10
Classifier: Programming Language :: Python :: 3.11
Project-URL: Documentation, https://github.com/frederikvanhevel/extract-transform
Project-URL: Repository, https://github.com/frederikvanhevel/extract-transform
